X500LinesOrLess/README.md
X500LinesOrLess/__init__.py
X500LinesOrLess/__main__.py
X500LinesOrLess/file.epub
X500LinesOrLess/index.html
X500LinesOrLess/css/__init__.py
X500LinesOrLess/css/annotations.css
X500LinesOrLess/css/main.css
X500LinesOrLess/css/normalize.css
X500LinesOrLess/css/popup.css
X500LinesOrLess/font/__init__.py
X500LinesOrLess/font/fontello.eot
X500LinesOrLess/font/fontello.svg
X500LinesOrLess/font/fontello.ttf
X500LinesOrLess/font/fontello.woff
X500LinesOrLess/img/__init__.py
X500LinesOrLess/img/annotator-glyph-sprite.png
X500LinesOrLess/img/annotator-icon-sprite.png
X500LinesOrLess/img/apple-touch-icon.png
X500LinesOrLess/img/cancelfullscreen.png
X500LinesOrLess/img/close.png
X500LinesOrLess/img/fullscreen.png
X500LinesOrLess/img/loader.gif
X500LinesOrLess/img/menu-icon.png
X500LinesOrLess/img/save.png
X500LinesOrLess/img/saved.png
X500LinesOrLess/img/settings-s.png
X500LinesOrLess/img/settings.png
X500LinesOrLess/img/star.png
X500LinesOrLess/js/__init__.py
X500LinesOrLess/js/epub.js
X500LinesOrLess/js/epub.min.js
X500LinesOrLess/js/epub.min.map
X500LinesOrLess/js/hooks.min.js
X500LinesOrLess/js/hooks.min.map
X500LinesOrLess/js/reader.js
X500LinesOrLess/js/reader.js.map
X500LinesOrLess/js/reader.min.js
X500LinesOrLess/js/reader.min.map
X500LinesOrLess/js/hooks/__init__.py
X500LinesOrLess/js/hooks/extensions/__init__.py
X500LinesOrLess/js/hooks/extensions/highlight.js
X500LinesOrLess/js/libs/__init__.py
X500LinesOrLess/js/libs/jquery.min.js
X500LinesOrLess/js/libs/localforage.min.js
X500LinesOrLess/js/libs/screenfull.js
X500LinesOrLess/js/libs/screenfull.min.js
X500LinesOrLess/js/libs/zip.min.js
X500LinesOrLess/js/plugins/__init__.py
X500LinesOrLess/js/plugins/hypothesis.js
X500LinesOrLess/js/plugins/search.js
x500_lines_or_less-2024.2.29.0.dist-info/METADATA
x500_lines_or_less-2024.2.29.0.dist-info/WHEEL
x500_lines_or_less-2024.2.29.0.dist-info/entry_points.txt
x500_lines_or_less-2024.2.29.0.dist-info/top_level.txt
x500_lines_or_less-2024.2.29.0.dist-info/RECORD
